DDCCore/APICore.py
DDCCore/__init__.py
DDCSDK/__init__.py
DDCSDK/sdk.py
DDCSDK/setup.py
DDCSDK/__pycache__/__init__.cpython-310.pyc
src/DDCAPI.py
src/__init__.py
src/setup.py
ddc_api_sdk-1.0.3.dist-info/METADATA
ddc_api_sdk-1.0.3.dist-info/WHEEL
ddc_api_sdk-1.0.3.dist-info/top_level.txt
ddc_api_sdk-1.0.3.dist-info/RECORD
