Metadata-Version: 2.1
Name: ddc-api-sdk
Version: 1.0.3
Summary: Ding Dang Cats HTTP API Python DDCCore
Home-page: UNKNOWN
Author: ddc
Author-email: 
License: MIT
Platform: UNKNOWN
Requires-Python: >=3.9
